{
  "name": "GPIO",
  "type": "ARM",
  "dependenceList": [],
  "srcDirs": [
    ".eide/deps",
    "Core",
    "Drivers"
  ],
  "virtualFolder": {
    "name": "<virtual_root>",
    "files": [
      {
        "path": "startup_stm32f103xb.s"
      }
    ],
    "folders": []
  },
  "outDir": "build",
  "deviceName": null,
  "packDir": null,
  "miscInfo": {
    "uid": "8364de2a182e7d015c68820e9346a0b7"
  },
  "targets": {
    "Debug": {
      "excludeList": [],
      "toolchain": "GCC",
      "compileConfig": {
        "cpuType": "Cortex-M3",
        "floatingPointHardware": "none",
        "scatterFilePath": "STM32F103C8Tx_FLASH.ld",
        "useCustomScatterFile": true,
        "storageLayout": {
          "RAM": [],
          "ROM": []
        },
        "options": "null"
      },
      "uploader": "STLink",
      "uploadConfig": {
        "bin": "",
        "proType": "SWD",
        "resetMode": "default",
        "runAfterProgram": true,
        "speed": 4000,
        "address": "0x08000000",
        "elFile": "None",
        "optionBytes": ".eide/debug.st.option.bytes.ini",
        "otherCmds": ""
      },
      "uploadConfigMap": {
        "JLink": {
          "bin": "",
          "baseAddr": "",
          "cpuInfo": {
            "vendor": "null",
            "cpuName": "null"
          },
          "proType": 1,
          "speed": 8000,
          "otherCmds": ""
        }
      },
      "custom_dep": {
        "name": "default",
        "incList": [
          ".eide/deps"
        ],
        "libList": [],
        "sourceDirList": [],
        "defineList": [
          "USE_HAL_DRIVER",
          "STM32F103xB"
        ]
      }
    }
  },
  "version": "3.3"
}